SyncAi/__init__.py
SyncAi/cli.py
SyncAi/main.py
SyncAi-6.0.dist-info/LICENSE
SyncAi-6.0.dist-info/METADATA
SyncAi-6.0.dist-info/WHEEL
SyncAi-6.0.dist-info/entry_points.txt
SyncAi-6.0.dist-info/top_level.txt
SyncAi-6.0.dist-info/RECORD
