Metadata-Version: 2.1
Name: SyncAi
Version: 6.0
Summary: AI designed for cybersecurity professionals, ethical hackers, Malware, and penetration testers. It assists in vulnerability analysis, security script generation, and cybersecurity research, Backdoor implementation.
Home-page: https://github.com/DevZ44d/SyncAi
Author: deep
Author-email: AsyncPy@proton.me
License: MIT
Classifier: Programming Language :: Python :: 3
Classifier: License :: OSI Approved :: MIT License
Classifier: Operating System :: OS Independent
Requires-Python: >=3.6
License-File: LICENSE
